pytest_cdist/__init__.py
pytest_cdist/check.py
pytest_cdist/plugin.py
pytest_cdist/py.typed
pytest_cdist-0.5.1.dist-info/METADATA
pytest_cdist-0.5.1.dist-info/WHEEL
pytest_cdist-0.5.1.dist-info/entry_points.txt
pytest_cdist-0.5.1.dist-info/licenses/LICENCE
pytest_cdist-0.5.1.dist-info/RECORD
